onp2p/__init__.py
onp2p/binding.py
onp2p/libmath_operations.dylib
onp2p/libmath_operations.so
onp2p/libmath_operations_arm.dylib
onp2p/libtor_operations.dylib
onp2p/libtor_operations.so
onp2p/libtor_operations_arm.dylib
onp2p/shell.py
onp2p/tor_checks.py
onp2p/wrapper.py
onp2p-0.0.2.33.dist-info/LICENSE
onp2p-0.0.2.33.dist-info/METADATA
onp2p-0.0.2.33.dist-info/WHEEL
onp2p-0.0.2.33.dist-info/entry_points.txt
onp2p-0.0.2.33.dist-info/top_level.txt
onp2p-0.0.2.33.dist-info/RECORD
