Metadata-Version: 2.1
Name: onp2p
Version: 0.0.2.33
Summary: Basic mathematical operations using CFFI
Home-page: https://github.com/enricozanardo/onp2p.git
Author: Enrico Zanardo
Author-email: enrico.zanardo101@gmail.com
Classifier: Programming Language :: Python :: 3
Classifier: License :: OSI Approved :: GNU Affero General Public License v3 or later (AGPLv3+)
Classifier: Operating System :: OS Independent
Classifier: Development Status :: 1 - Planning
Requires-Python: >=3.11
License-File: LICENSE
Requires-Dist: cffi
Requires-Dist: pyfiglet
